flipcache/__init__.py
flipcache/et.py
flipcache/fifo_dict.py
flipcache/flipcache.py
flipcache/lru_dict.py
flipcache-1.3.dist-info/METADATA
flipcache-1.3.dist-info/WHEEL
flipcache-1.3.dist-info/licenses/LICENSE
flipcache-1.3.dist-info/RECORD
