Metadata-Version: 2.4
Name: FlipCache
Version: 1.3
Summary: Redis-backed hybrid caching for lightning-fast Python data access
Project-URL: Homepage, https://github.com/goodeejay/FlipCache
Project-URL: Issues, https://github.com/goodeejay/FlipCache/issues
Author-email: Jasur Yusupov <jasuryusupov14@gmail.com>
Maintainer-email: Jasur Yusupov <jasuryusupov14@gmail.com>
License-Expression: MIT
License-File: LICENSE
Keywords: cache,expiring_dict,fast_access,limited_dict,memory,redis,wrapper
Classifier: Intended Audience :: Developers
Classifier: Intended Audience :: System Administrators
Classifier: License :: OSI Approved :: MIT License
Classifier: Operating System :: OS Independent
Classifier: Programming Language :: Python :: 3
Classifier: Topic :: Software Development :: Libraries :: Python Modules
Classifier: Typing :: Typed
Requires-Python: >=3.6
Requires-Dist: redis
